sparc/__init__.py
sparc/block.py
sparc/generator.py
sparc/inversion.py
sparc/sparc.py
sparc/speech.py
sparc/spk_encoder.py
sparc/src_extractor.py
speech_articulatory_coding-0.1.0.dist-info/METADATA
speech_articulatory_coding-0.1.0.dist-info/WHEEL
speech_articulatory_coding-0.1.0.dist-info/top_level.txt
speech_articulatory_coding-0.1.0.dist-info/RECORD
