Metadata-Version: 2.2
Name: speech-articulatory-coding
Version: 0.1.0
Summary: Python code for analyzing and synthesizing articulatory features of speech
Home-page: https://github.com/Berkeley-Speech-Group/Speech-Articulatory-Coding
Author: Cheol Jun Cho
Author-email: cheoljun@berkeley.edu
License: MIT
Classifier: Programming Language :: Python :: 3
Classifier: License :: OSI Approved :: MIT License
Classifier: Operating System :: OS Independent
Requires-Python: >=3.8
Requires-Dist: numpy
Requires-Dist: soundfile
Requires-Dist: librosa
Requires-Dist: torch
Requires-Dist: torchaudio
Requires-Dist: transformers
Requires-Dist: torchcrepe
Requires-Dist: huggingface-hub
Requires-Dist: matplotlib
Requires-Dist: tqdm
Requires-Dist: penn
Dynamic: author
Dynamic: author-email
Dynamic: classifier
Dynamic: description
Dynamic: description-content-type
Dynamic: home-page
Dynamic: license
Dynamic: requires-dist
Dynamic: requires-python
Dynamic: summary
